example/example.py
horiba_raman_ccoverstreet/__init__.py
horiba_raman_ccoverstreet/mapping.py
horiba_raman_ccoverstreet/old_mapping.py
quickplot_example/quickplot_example.py
rotated_rect_map/rotated.py
horiba_raman_ccoverstreet-0.0.9.dist-info/LICENSE
horiba_raman_ccoverstreet-0.0.9.dist-info/METADATA
horiba_raman_ccoverstreet-0.0.9.dist-info/WHEEL
horiba_raman_ccoverstreet-0.0.9.dist-info/top_level.txt
horiba_raman_ccoverstreet-0.0.9.dist-info/RECORD
