Metadata-Version: 2.1
Name: horiba_raman_ccoverstreet
Version: 0.0.9
Summary: Package for processing Horiba LabRAM HR data
Author: Cale Overstreet
Project-URL: Source, https://github.com/ccoverstreet/horiba-raman
Project-URL: Documentation,  https://horiba-raman.readthedocs.io/en/latest/horiba_raman_ccoverstreet.html
Requires-Python: >3.8
License-File: LICENSE
Requires-Dist: pillow
Requires-Dist: numpy
Requires-Dist: matplotlib
